{"updatedAt":"2026-03-06T04:26:46.843Z","teams":[{"id":784,"code":"CAN","name":"Canada","flag":"🇨🇦","pool":"A"},{"id":792,"code":"COL","name":"Colombia","flag":"🇨🇴","pool":"A"},{"id":798,"code":"CUB","name":"Cuba","flag":"🇨🇺","pool":"A"},{"id":890,"code":"PAN","name":"Panama","flag":"🇵🇦","pool":"A"},{"id":897,"code":"PUR","name":"Puerto Rico","flag":"🇵🇷","pool":"A"},{"id":776,"code":"BRA","name":"Brazil","flag":"🇧🇷","pool":"B"},{"id":821,"code":"GBR","name":"Great Britain","flag":"🇬🇧","pool":"B"},{"id":841,"code":"ITA","name":"Italy","flag":"🇮🇹","pool":"B"},{"id":867,"code":"MEX","name":"Mexico","flag":"🇲🇽","pool":"B"},{"id":940,"code":"USA","name":"United States","flag":"🇺🇸","pool":"B"},{"id":760,"code":"AUS","name":"Australia","flag":"🇦🇺","pool":"C"},{"id":791,"code":"TPE","name":"Chinese Taipei","flag":"🏌","pool":"C"},{"id":800,"code":"CZE","name":"Czechia","flag":"🇨🇿","pool":"C"},{"id":843,"code":"JPN","name":"Japan","flag":"🇯🇵","pool":"C"},{"id":1171,"code":"KOR","name":"South Korea","flag":"🇰🇷","pool":"C"},{"id":805,"code":"DOM","name":"Dominican Republic","flag":"🇩🇴","pool":"D"},{"id":840,"code":"ISR","name":"Israel","flag":"🇮🇱","pool":"D"},{"id":878,"code":"NED","name":"Netherlands","flag":"🇳🇱","pool":"D"},{"id":881,"code":"NCA","name":"Nicaragua","flag":"🇳🇮","pool":"D"},{"id":944,"code":"VEN","name":"Venezuela","flag":"🇻🇪","pool":"D"}],"games":[{"id":788120,"startTime":"2026-03-05T03:00:00Z","officialDate":"2026-03-05","status":"Final","statusCode":"F","description":"Pool C","seriesDescription":"World Baseball Classic Pool Play","venue":"Tokyo Dome","dayNight":"day","away":{"id":791,"name":"Chinese Taipei","code":"TPE","score":0,"isWinner":false,"record":"0-1"},"home":{"id":760,"name":"Australia","code":"AUS","score":3,"isWinner":true,"record":"1-0"},"isTBD":false},{"id":788115,"startTime":"2026-03-05T10:00:00Z","officialDate":"2026-03-05","status":"Final","statusCode":"F","description":"Pool C","seriesDescription":"World Baseball Classic Pool Play","venue":"Tokyo Dome","dayNight":"night","away":{"id":800,"name":"Czechia","code":"CZE","score":4,"isWinner":false,"record":"0-1"},"home":{"id":1171,"name":"South Korea","code":"KOR","score":11,"isWinner":true,"record":"1-0"},"isTBD":false},{"id":788116,"startTime":"2026-03-06T03:00:00Z","officialDate":"2026-03-06","status":"In Progress","statusCode":"I","description":"Pool C","seriesDescription":"World Baseball Classic Pool Play","venue":"Tokyo Dome","dayNight":"day","away":{"id":760,"name":"Australia","code":"AUS","score":3,"isWinner":null,"record":"1-0"},"home":{"id":800,"name":"Czechia","code":"CZE","score":1,"isWinner":null,"record":"0-1"},"isTBD":false},{"id":788114,"startTime":"2026-03-06T10:00:00Z","officialDate":"2026-03-06","status":"Scheduled","statusCode":"S","description":"Pool C","seriesDescription":"World Baseball Classic Pool Play","venue":"Tokyo Dome","dayNight":"night","away":{"id":843,"name":"Japan","code":"JPN","score":null,"isWinner":null,"record":"0-0"},"home":{"id":791,"name":"Chinese Taipei","code":"TPE","score":null,"isWinner":null,"record":"0-1"},"isTBD":false},{"id":788139,"startTime":"2026-03-06T16:00:00Z","officialDate":"2026-03-06","status":"Scheduled","statusCode":"S","description":"Pool A","seriesDescription":"World Baseball Classic Pool Play","venue":"Hiram Bithorn Stadium","dayNight":"day","away":{"id":798,"name":"Cuba","code":"CUB","score":null,"isWinner":null,"record":"0-0"},"home":{"id":890,"name":"Panama","code":"PAN","score":null,"isWinner":null,"record":"0-0"},"isTBD":false},{"id":788110,"startTime":"2026-03-06T17:00:00Z","officialDate":"2026-03-06","status":"Scheduled","statusCode":"S","description":"Pool D","seriesDescription":"World Baseball Classic Pool Play","venue":"loanDepot park","dayNight":"day","away":{"id":878,"name":"Netherlands","code":"NED","score":null,"isWinner":null,"record":"0-0"},"home":{"id":944,"name":"Venezuela","code":"VEN","score":null,"isWinner":null,"record":"0-0"},"isTBD":false},{"id":788129,"startTime":"2026-03-06T18:00:00Z","officialDate":"2026-03-06","status":"Scheduled","statusCode":"S","description":"Pool B","seriesDescription":"World Baseball Classic Pool Play","venue":"Daikin Park","dayNight":"day","away":{"id":867,"name":"Mexico","code":"MEX","score":null,"isWinner":null,"record":"0-0"},"home":{"id":821,"name":"Great Britain","code":"GBR","score":null,"isWinner":null,"record":"0-0"},"isTBD":false},{"id":788136,"startTime":"2026-03-06T23:00:00Z","officialDate":"2026-03-06","status":"Scheduled","statusCode":"S","description":"Pool A","seriesDescription":"World Baseball Classic Pool Play","venue":"Hiram Bithorn Stadium","dayNight":"night","away":{"id":897,"name":"Puerto Rico","code":"PUR","score":null,"isWinner":null,"record":"0-0"},"home":{"id":792,"name":"Colombia","code":"COL","score":null,"isWinner":null,"record":"0-0"},"isTBD":false},{"id":788105,"startTime":"2026-03-07T00:00:00Z","officialDate":"2026-03-06","status":"Scheduled","statusCode":"S","description":"Pool D","seriesDescription":"World Baseball Classic Pool Play","venue":"loanDepot park","dayNight":"night","away":{"id":881,"name":"Nicaragua","code":"NCA","score":null,"isWinner":null,"record":"0-0"},"home":{"id":805,"name":"Dominican Republic","code":"DOM","score":null,"isWinner":null,"record":"0-0"},"isTBD":false},{"id":788128,"startTime":"2026-03-07T01:00:00Z","officialDate":"2026-03-06","status":"Scheduled","statusCode":"S","description":"Pool B","seriesDescription":"World Baseball Classic Pool Play","venue":"Daikin Park","dayNight":"night","away":{"id":940,"name":"United States","code":"USA","score":null,"isWinner":null,"record":"0-0"},"home":{"id":776,"name":"Brazil","code":"BRA","score":null,"isWinner":null,"record":"0-0"},"isTBD":false},{"id":788117,"startTime":"2026-03-07T03:00:00Z","officialDate":"2026-03-07","status":"Scheduled","statusCode":"S","description":"Pool C","seriesDescription":"World Baseball Classic Pool Play","venue":"Tokyo Dome","dayNight":"day","away":{"id":791,"name":"Chinese Taipei","code":"TPE","score":null,"isWinner":null,"record":"0-1"},"home":{"id":800,"name":"Czechia","code":"CZE","score":null,"isWinner":null,"record":"0-1"},"isTBD":false},{"id":788118,"startTime":"2026-03-07T10:00:00Z","officialDate":"2026-03-07","status":"Scheduled","statusCode":"S","description":"Pool C","seriesDescription":"World Baseball Classic Pool Play","venue":"Tokyo Dome","dayNight":"night","away":{"id":1171,"name":"South Korea","code":"KOR","score":null,"isWinner":null,"record":"1-0"},"home":{"id":843,"name":"Japan","code":"JPN","score":null,"isWinner":null,"record":"0-0"},"isTBD":false},{"id":788138,"startTime":"2026-03-07T16:00:00Z","officialDate":"2026-03-07","status":"Scheduled","statusCode":"S","description":"Pool A","seriesDescription":"World Baseball Classic Pool Play","venue":"Hiram Bithorn Stadium","dayNight":"day","away":{"id":792,"name":"Colombia","code":"COL","score":null,"isWinner":null,"record":"0-0"},"home":{"id":784,"name":"Canada","code":"CAN","score":null,"isWinner":null,"record":"0-0"},"isTBD":false},{"id":788108,"startTime":"2026-03-07T17:00:00Z","officialDate":"2026-03-07","status":"Scheduled","statusCode":"S","description":"Pool D","seriesDescription":"World Baseball Classic Pool Play","venue":"loanDepot park","dayNight":"day","away":{"id":881,"name":"Nicaragua","code":"NCA","score":null,"isWinner":null,"record":"0-0"},"home":{"id":878,"name":"Netherlands","code":"NED","score":null,"isWinner":null,"record":"0-0"},"isTBD":false},{"id":788126,"startTime":"2026-03-07T18:00:00Z","officialDate":"2026-03-07","status":"Scheduled","statusCode":"S","description":"Pool B","seriesDescription":"World Baseball Classic Pool Play","venue":"Daikin Park","dayNight":"day","away":{"id":776,"name":"Brazil","code":"BRA","score":null,"isWinner":null,"record":"0-0"},"home":{"id":841,"name":"Italy","code":"ITA","score":null,"isWinner":null,"record":"0-0"},"isTBD":false},{"id":788137,"startTime":"2026-03-07T23:00:00Z","officialDate":"2026-03-07","status":"Scheduled","statusCode":"S","description":"Pool A","seriesDescription":"World Baseball Classic Pool Play","venue":"Hiram Bithorn Stadium","dayNight":"night","away":{"id":890,"name":"Panama","code":"PAN","score":null,"isWinner":null,"record":"0-0"},"home":{"id":897,"name":"Puerto Rico","code":"PUR","score":null,"isWinner":null,"record":"0-0"},"isTBD":false},{"id":788107,"startTime":"2026-03-08T00:00:00Z","officialDate":"2026-03-07","status":"Scheduled","statusCode":"S","description":"Pool D","seriesDescription":"World Baseball Classic Pool Play","venue":"loanDepot park","dayNight":"night","away":{"id":840,"name":"Israel","code":"ISR","score":null,"isWinner":null,"record":"0-0"},"home":{"id":944,"name":"Venezuela","code":"VEN","score":null,"isWinner":null,"record":"0-0"},"isTBD":false},{"id":788127,"startTime":"2026-03-08T01:00:00Z","officialDate":"2026-03-07","status":"Scheduled","statusCode":"S","description":"Pool B","seriesDescription":"World Baseball Classic Pool Play","venue":"Daikin Park","dayNight":"night","away":{"id":821,"name":"Great Britain","code":"GBR","score":null,"isWinner":null,"record":"0-0"},"home":{"id":940,"name":"United States","code":"USA","score":null,"isWinner":null,"record":"0-0"},"isTBD":false},{"id":788113,"startTime":"2026-03-08T03:00:00Z","officialDate":"2026-03-08","status":"Scheduled","statusCode":"S","description":"Pool C","seriesDescription":"World Baseball Classic Pool Play","venue":"Tokyo Dome","dayNight":"day","away":{"id":791,"name":"Chinese Taipei","code":"TPE","score":null,"isWinner":null,"record":"0-1"},"home":{"id":1171,"name":"South Korea","code":"KOR","score":null,"isWinner":null,"record":"1-0"},"isTBD":false},{"id":788109,"startTime":"2026-03-08T10:00:00Z","officialDate":"2026-03-08","status":"Scheduled","statusCode":"S","description":"Pool C","seriesDescription":"World Baseball Classic Pool Play","venue":"Tokyo Dome","dayNight":"night","away":{"id":760,"name":"Australia","code":"AUS","score":null,"isWinner":null,"record":"1-0"},"home":{"id":843,"name":"Japan","code":"JPN","score":null,"isWinner":null,"record":"0-0"},"isTBD":false},{"id":788135,"startTime":"2026-03-08T16:00:00Z","officialDate":"2026-03-08","status":"Scheduled","statusCode":"S","description":"Pool A","seriesDescription":"World Baseball Classic Pool Play","venue":"Hiram Bithorn Stadium","dayNight":"day","away":{"id":792,"name":"Colombia","code":"COL","score":null,"isWinner":null,"record":"0-0"},"home":{"id":798,"name":"Cuba","code":"CUB","score":null,"isWinner":null,"record":"0-0"},"isTBD":false},{"id":788106,"startTime":"2026-03-08T16:00:00Z","officialDate":"2026-03-08","status":"Scheduled","statusCode":"S","description":"Pool D","seriesDescription":"World Baseball Classic Pool Play","venue":"loanDepot park","dayNight":"day","away":{"id":878,"name":"Netherlands","code":"NED","score":null,"isWinner":null,"record":"0-0"},"home":{"id":805,"name":"Dominican Republic","code":"DOM","score":null,"isWinner":null,"record":"0-0"},"isTBD":false},{"id":788124,"startTime":"2026-03-08T17:00:00Z","officialDate":"2026-03-08","status":"Scheduled","statusCode":"S","description":"Pool B","seriesDescription":"World Baseball Classic Pool Play","venue":"Daikin Park","dayNight":"day","away":{"id":821,"name":"Great Britain","code":"GBR","score":null,"isWinner":null,"record":"0-0"},"home":{"id":841,"name":"Italy","code":"ITA","score":null,"isWinner":null,"record":"0-0"},"isTBD":false},{"id":788104,"startTime":"2026-03-08T23:00:00Z","officialDate":"2026-03-08","status":"Scheduled","statusCode":"S","description":"Pool D","seriesDescription":"World Baseball Classic Pool Play","venue":"loanDepot park","dayNight":"night","away":{"id":881,"name":"Nicaragua","code":"NCA","score":null,"isWinner":null,"record":"0-0"},"home":{"id":840,"name":"Israel","code":"ISR","score":null,"isWinner":null,"record":"0-0"},"isTBD":false},{"id":788134,"startTime":"2026-03-08T23:00:00Z","officialDate":"2026-03-08","status":"Scheduled","statusCode":"S","description":"Pool A","seriesDescription":"World Baseball Classic Pool Play","venue":"Hiram Bithorn Stadium","dayNight":"night","away":{"id":890,"name":"Panama","code":"PAN","score":null,"isWinner":null,"record":"0-0"},"home":{"id":784,"name":"Canada","code":"CAN","score":null,"isWinner":null,"record":"0-0"},"isTBD":false},{"id":788125,"startTime":"2026-03-09T00:00:00Z","officialDate":"2026-03-08","status":"Scheduled","statusCode":"S","description":"Pool B","seriesDescription":"World Baseball Classic Pool Play","venue":"Daikin Park","dayNight":"night","away":{"id":776,"name":"Brazil","code":"BRA","score":null,"isWinner":null,"record":"0-0"},"home":{"id":867,"name":"Mexico","code":"MEX","score":null,"isWinner":null,"record":"0-0"},"isTBD":false},{"id":788112,"startTime":"2026-03-09T10:00:00Z","officialDate":"2026-03-09","status":"Scheduled","statusCode":"S","description":"Pool C","seriesDescription":"World Baseball Classic Pool Play","venue":"Tokyo Dome","dayNight":"night","away":{"id":1171,"name":"South Korea","code":"KOR","score":null,"isWinner":null,"record":"1-0"},"home":{"id":760,"name":"Australia","code":"AUS","score":null,"isWinner":null,"record":"1-0"},"isTBD":false},{"id":788103,"startTime":"2026-03-09T16:00:00Z","officialDate":"2026-03-09","status":"Scheduled","statusCode":"S","description":"Pool D","seriesDescription":"World Baseball Classic Pool Play","venue":"loanDepot park","dayNight":"day","away":{"id":805,"name":"Dominican Republic","code":"DOM","score":null,"isWinner":null,"record":"0-0"},"home":{"id":840,"name":"Israel","code":"ISR","score":null,"isWinner":null,"record":"0-0"},"isTBD":false},{"id":788133,"startTime":"2026-03-09T16:00:00Z","officialDate":"2026-03-09","status":"Scheduled","statusCode":"S","description":"Pool A","seriesDescription":"World Baseball Classic Pool Play","venue":"Hiram Bithorn Stadium","dayNight":"day","away":{"id":792,"name":"Colombia","code":"COL","score":null,"isWinner":null,"record":"0-0"},"home":{"id":890,"name":"Panama","code":"PAN","score":null,"isWinner":null,"record":"0-0"},"isTBD":false},{"id":788123,"startTime":"2026-03-09T17:00:00Z","officialDate":"2026-03-09","status":"Scheduled","statusCode":"S","description":"Pool B","seriesDescription":"World Baseball Classic Pool Play","venue":"Daikin Park","dayNight":"day","away":{"id":776,"name":"Brazil","code":"BRA","score":null,"isWinner":null,"record":"0-0"},"home":{"id":821,"name":"Great Britain","code":"GBR","score":null,"isWinner":null,"record":"0-0"},"isTBD":false},{"id":788131,"startTime":"2026-03-09T23:00:00Z","officialDate":"2026-03-09","status":"Scheduled","statusCode":"S","description":"Pool A","seriesDescription":"World Baseball Classic Pool Play","venue":"Hiram Bithorn Stadium","dayNight":"night","away":{"id":798,"name":"Cuba","code":"CUB","score":null,"isWinner":null,"record":"0-0"},"home":{"id":897,"name":"Puerto Rico","code":"PUR","score":null,"isWinner":null,"record":"0-0"},"isTBD":false},{"id":788099,"startTime":"2026-03-09T23:00:00Z","officialDate":"2026-03-09","status":"Scheduled","statusCode":"S","description":"Pool D","seriesDescription":"World Baseball Classic Pool Play","venue":"loanDepot park","dayNight":"night","away":{"id":944,"name":"Venezuela","code":"VEN","score":null,"isWinner":null,"record":"0-0"},"home":{"id":881,"name":"Nicaragua","code":"NCA","score":null,"isWinner":null,"record":"0-0"},"isTBD":false},{"id":788122,"startTime":"2026-03-10T00:00:00Z","officialDate":"2026-03-09","status":"Scheduled","statusCode":"S","description":"Pool B","seriesDescription":"World Baseball Classic Pool Play","venue":"Daikin Park","dayNight":"night","away":{"id":867,"name":"Mexico","code":"MEX","score":null,"isWinner":null,"record":"0-0"},"home":{"id":940,"name":"United States","code":"USA","score":null,"isWinner":null,"record":"0-0"},"isTBD":false},{"id":788111,"startTime":"2026-03-10T10:00:00Z","officialDate":"2026-03-10","status":"Scheduled","statusCode":"S","description":"Pool C","seriesDescription":"World Baseball Classic Pool Play","venue":"Tokyo Dome","dayNight":"night","away":{"id":800,"name":"Czechia","code":"CZE","score":null,"isWinner":null,"record":"0-1"},"home":{"id":843,"name":"Japan","code":"JPN","score":null,"isWinner":null,"record":"0-0"},"isTBD":false},{"id":788102,"startTime":"2026-03-10T23:00:00Z","officialDate":"2026-03-10","status":"Scheduled","statusCode":"S","description":"Pool D","seriesDescription":"World Baseball Classic Pool Play","venue":"loanDepot park","dayNight":"night","away":{"id":840,"name":"Israel","code":"ISR","score":null,"isWinner":null,"record":"0-0"},"home":{"id":878,"name":"Netherlands","code":"NED","score":null,"isWinner":null,"record":"0-0"},"isTBD":false},{"id":788132,"startTime":"2026-03-10T23:00:00Z","officialDate":"2026-03-10","status":"Scheduled","statusCode":"S","description":"Pool A","seriesDescription":"World Baseball Classic Pool Play","venue":"Hiram Bithorn Stadium","dayNight":"night","away":{"id":784,"name":"Canada","code":"CAN","score":null,"isWinner":null,"record":"0-0"},"home":{"id":897,"name":"Puerto Rico","code":"PUR","score":null,"isWinner":null,"record":"0-0"},"isTBD":false},{"id":788119,"startTime":"2026-03-11T01:00:00Z","officialDate":"2026-03-10","status":"Scheduled","statusCode":"S","description":"Pool B","seriesDescription":"World Baseball Classic Pool Play","venue":"Daikin Park","dayNight":"night","away":{"id":841,"name":"Italy","code":"ITA","score":null,"isWinner":null,"record":"0-0"},"home":{"id":940,"name":"United States","code":"USA","score":null,"isWinner":null,"record":"0-0"},"isTBD":false},{"id":788130,"startTime":"2026-03-11T19:00:00Z","officialDate":"2026-03-11","status":"Scheduled","statusCode":"S","description":"Pool A","seriesDescription":"World Baseball Classic Pool Play","venue":"Hiram Bithorn Stadium","dayNight":"day","away":{"id":784,"name":"Canada","code":"CAN","score":null,"isWinner":null,"record":"0-0"},"home":{"id":798,"name":"Cuba","code":"CUB","score":null,"isWinner":null,"record":"0-0"},"isTBD":false},{"id":788121,"startTime":"2026-03-11T23:00:00Z","officialDate":"2026-03-11","status":"Scheduled","statusCode":"S","description":"Pool B","seriesDescription":"World Baseball Classic Pool Play","venue":"Daikin Park","dayNight":"night","away":{"id":841,"name":"Italy","code":"ITA","score":null,"isWinner":null,"record":"0-0"},"home":{"id":867,"name":"Mexico","code":"MEX","score":null,"isWinner":null,"record":"0-0"},"isTBD":false},{"id":788101,"startTime":"2026-03-12T00:00:00Z","officialDate":"2026-03-11","status":"Scheduled","statusCode":"S","description":"Pool D","seriesDescription":"World Baseball Classic Pool Play","venue":"loanDepot park","dayNight":"night","away":{"id":805,"name":"Dominican Republic","code":"DOM","score":null,"isWinner":null,"record":"0-0"},"home":{"id":944,"name":"Venezuela","code":"VEN","score":null,"isWinner":null,"record":"0-0"},"isTBD":false},{"id":788095,"startTime":"2026-03-13T22:30:00Z","officialDate":"2026-03-13","status":"Scheduled","statusCode":"S","description":"Quarterfinal 1: Pool C Runner-Up vs. Pool D Winner","seriesDescription":"World Baseball Classic Quarterfinals","venue":"loanDepot park","dayNight":"night","away":{"id":3006,"name":"Pool C Runner-Up","code":"TBD","score":null,"isWinner":null,"record":"0-0"},"home":{"id":3009,"name":"Pool D Winner","code":"TBD","score":null,"isWinner":null,"record":"0-0"},"isTBD":true},{"id":788100,"startTime":"2026-03-14T00:00:00Z","officialDate":"2026-03-13","status":"Scheduled","statusCode":"S","description":"Quarterfinal 2: Pool A Runner-Up vs. Pool B Winner","seriesDescription":"World Baseball Classic Quarterfinals","venue":"Daikin Park","dayNight":"night","away":{"id":3002,"name":"Pool A Runner-Up","code":"TBD","score":null,"isWinner":null,"record":"0-0"},"home":{"id":3005,"name":"Pool B Winner","code":"TBD","score":null,"isWinner":null,"record":"0-0"},"isTBD":true},{"id":788098,"startTime":"2026-03-14T19:00:00Z","officialDate":"2026-03-14","status":"Scheduled","statusCode":"S","description":"Quarterfinal 3: Pool B Runner-Up vs. Pool A Winner","seriesDescription":"World Baseball Classic Quarterfinals","venue":"Daikin Park","dayNight":"day","away":{"id":3004,"name":"Pool B Runner-Up","code":"TBD","score":null,"isWinner":null,"record":"0-0"},"home":{"id":3003,"name":"Pool A Winner","code":"TBD","score":null,"isWinner":null,"record":"0-0"},"isTBD":true},{"id":788097,"startTime":"2026-03-15T01:00:00Z","officialDate":"2026-03-14","status":"Scheduled","statusCode":"S","description":"Quarterfinal 4: Pool D Runner-Up vs. Pool C Winner","seriesDescription":"World Baseball Classic Quarterfinals","venue":"loanDepot park","dayNight":"night","away":{"id":3008,"name":"Pool D Runner-Up","code":"TBD","score":null,"isWinner":null,"record":"0-0"},"home":{"id":3007,"name":"Pool C Winner","code":"TBD","score":null,"isWinner":null,"record":"0-0"},"isTBD":true},{"id":788096,"startTime":"2026-03-16T00:00:00Z","officialDate":"2026-03-15","status":"Scheduled","statusCode":"S","description":"Semifinal 1: Quarterfinal Winners TBD","seriesDescription":"World Baseball Classic Semifinals","venue":"loanDepot park","dayNight":"night","away":{"id":4561,"name":"Quarterfinal Winner","code":"QW","score":null,"isWinner":null,"record":"0-0"},"home":{"id":4560,"name":"Quarterfinal Winner","code":"QW","score":null,"isWinner":null,"record":"0-0"},"isTBD":true},{"id":788093,"startTime":"2026-03-17T00:00:00Z","officialDate":"2026-03-16","status":"Scheduled","statusCode":"S","description":"Semifinal 2: Quarterfinal Winners TBD","seriesDescription":"World Baseball Classic Semifinals","venue":"loanDepot park","dayNight":"night","away":{"id":4562,"name":"Quarterfinal Winner","code":"QW","score":null,"isWinner":null,"record":"0-0"},"home":{"id":4563,"name":"Quarterfinal Winner","code":"QW","score":null,"isWinner":null,"record":"0-0"},"isTBD":true},{"id":788094,"startTime":"2026-03-18T00:00:00Z","officialDate":"2026-03-17","status":"Scheduled","statusCode":"S","description":"Finals: Semifinal 1 Winner vs. Semifinal 2 Winner","seriesDescription":"World Baseball Classic Finals","venue":"loanDepot park","dayNight":"night","away":{"id":3010,"name":"Semifinal 1 Winner","code":"S1W","score":null,"isWinner":null,"record":"0-0"},"home":{"id":3011,"name":"Semifinal 2 Winner","code":"S2W","score":null,"isWinner":null,"record":"0-0"},"isTBD":true}]}